hidroaccess/__init__.py
hidroaccess/access.py
hidroaccess/decodes.py
hidroaccess_mbrond-1.0.0.dist-info/METADATA
hidroaccess_mbrond-1.0.0.dist-info/WHEEL
hidroaccess_mbrond-1.0.0.dist-info/top_level.txt
hidroaccess_mbrond-1.0.0.dist-info/RECORD
