Metadata-Version: 2.2
Name: hidroaccess_mBrond
Version: 1.0.0
Summary: Pacote para download de dados da ANA
Home-page: https://github.com/mBrond/AccessHidroWebService
Author: Miguel Brondani
Author-email: Miguel Brondani <brondani.miguel@gmail.com>
License: MIT
Project-URL: Homepage, https://github.com/mBrond/AccessHidroWebService
Project-URL: Issues, https://github.com/mBrond/AccessHidroWebService/issues
Classifier: Programming Language :: Python :: 3
Classifier: Operating System :: OS Independent
Classifier: License :: OSI Approved :: MIT License
Requires-Python: >=3.6
Dynamic: author
Dynamic: home-page
Dynamic: requires-python
